rexpgen/__init__.py
rexpgen/main.py
rexpgen-0.0.1.dist-info/LICENSE
rexpgen-0.0.1.dist-info/METADATA
rexpgen-0.0.1.dist-info/WHEEL
rexpgen-0.0.1.dist-info/top_level.txt
rexpgen-0.0.1.dist-info/RECORD
